{"data": [{"pkd_code": "20", "year": 2005, "revenue": 33341660.000000004, "profit": 1600320.0, "assets": 60014988.00000001, "debt": 2348770.0, "bankruptcies": 0, "num_companies": 449}, {"pkd_code": "20", "year": 2006, "revenue": 37446400.0, "profit": 1251110.0, "assets": 67403520.0, "debt": 2476290.0, "bankruptcies": 0, "num_companies": 412}, {"pkd_code": "20", "year": 2007, "revenue": 40324200.0, "profit": 2600700.0, "assets": 72583560.0, "debt": 2967390.0, "bankruptcies": 0, "num_companies": 421}, {"pkd_code": "20", "year": 2008, "revenue": 42770020.0, "profit": 1594250.0, "assets": 76986036.0, "debt": 1834140.0, "bankruptcies": 0, "num_companies": 452}, {"pkd_code": "20", "year": 2009, "revenue": 41483570.0, "profit": 1529530.0, "assets": 74670426.0, "debt": 2886440.0, "bankruptcies": 0, "num_companies": 464}, {"pkd_code": "20", "year": 2010, "revenue": 49121740.0, "profit": 2536940.0, "assets": 88419132.0, "debt": 3418310.0, "bankruptcies": 0, "num_companies": 468}, {"pkd_code": "20", "year": 2011, "revenue": 58427240.0, "profit": 3286890.0, "assets": 105169032.0, "debt": 3981280.0, "bankruptcies": 0, "num_companies": 471}, {"pkd_code": "20", "year": 2012, "revenue": 63742810.0, "profit": 2875240.0, "assets": 114737058.0, "debt": 4230010.0, "bankruptcies": 0, "num_companies": 504}, {"pkd_code": "20", "year": 2013, "revenue": 61667320.0, "profit": 3285530.0, "assets": 111001176.0, "debt": 3899780.0, "bankruptcies": 0, "num_companies": 489}, {"pkd_code": "20", "year": 2014, "revenue": 62363830.0, "profit": 3432020.0, "assets": 112254894.0, "debt": 4503120.0, "bankruptcies": 0, "num_companies": 511}, {"pkd_code": "20", "year": 2015, "revenue": 64242280.0, "profit": 4446640.0, "assets": 115636104.0, "debt": 5611130.0, "bankruptcies": 0, "num_companies": 506}, {"pkd_code": "20", "year": 2016, "revenue": 65735810.0, "profit": 5544290.0, "assets": 118324458.0, "debt": 7510070.0, "bankruptcies": 0, "num_companies": 530}, {"pkd_code": "20", "year": 2017, "revenue": 66133410.0, "profit": 4492190.0, "assets": 119040138.0, "debt": 7457260.0, "bankruptcies": 0, "num_companies": 497}, {"pkd_code": "20", "year": 2018, "revenue": 69077550.0, "profit": 3756690.0, "assets": 124339590.0, "debt": 8561000.0, "bankruptcies": 12, "num_companies": 503}, {"pkd_code": "20", "year": 2019, "revenue": 69506630.0, "profit": 3981920.0, "assets": 125111934.0, "debt": 9733510.0, "bankruptcies": 7, "num_companies": 497}, {"pkd_code": "20", "year": 2020, "revenue": 69202090.0, "profit": 4279270.0, "assets": 124563762.0, "debt": 10130070.0, "bankruptcies": 5, "num_companies": 520}, {"pkd_code": "20", "year": 2021, "revenue": 91952020.0, "profit": 7562510.0, "assets": 165513636.0, "debt": 11438250.0, "bankruptcies": 4, "num_companies": 516}, {"pkd_code": "20", "year": 2022, "revenue": 126655580.0, "profit": 7738820.0, "assets": 227980044.0, "debt": 10232130.0, "bankruptcies": 8, "num_companies": 541}, {"pkd_code": "20", "year": 2023, "revenue": 105340420.0, "profit": 762500.0, "assets": 189612756.0, "debt": 9029740.0, "bankruptcies": 9, "num_companies": 557}, {"pkd_code": "20", "year": 2024, "revenue": 104989600.0, "profit": 3432250.0, "assets": 188981280.0, "debt": 9124550.0, "bankruptcies": 10, "num_companies": 573}], "expires_at": "2025-12-07T08:12:05.555433"}